{
	"configurations" : 
	[
		{
			"directories" : 
			[
				{
					"build" : ".",
					"hasInstallRule" : true,
					"jsonFile" : "directory-.-Debug-062c03551d78bfc0affb.json",
					"minimumCMakeVersion" : 
					{
						"string" : "3.12"
					},
					"projectIndex" : 0,
					"source" : ".",
					"targetIndexes" : 
					[
						0,
						1,
						2,
						3,
						4,
						5,
						6
					]
				}
			],
			"name" : "Debug",
			"projects" : 
			[
				{
					"directoryIndexes" : 
					[
						0
					],
					"name" : "std_srvs",
					"targetIndexes" : 
					[
						0,
						1,
						2,
						3,
						4,
						5,
						6
					]
				}
			],
			"targets" : 
			[
				{
					"directoryIndex" : 0,
					"id" : "std_srvs::@6890427a1f51a3e7e1df",
					"jsonFile" : "target-std_srvs-Debug-84464fe58d1d50538c47.json",
					"name" : "std_srvs",
					"projectIndex" : 0
				},
				{
					"directoryIndex" : 0,
					"id" : "std_srvs__rosidl_generator_c::@6890427a1f51a3e7e1df",
					"jsonFile" : "target-std_srvs__rosidl_generator_c-Debug-1511b0b531cfef24bc1e.json",
					"name" : "std_srvs__rosidl_generator_c",
					"projectIndex" : 0
				},
				{
					"directoryIndex" : 0,
					"id" : "std_srvs__rosidl_typesupport_c::@6890427a1f51a3e7e1df",
					"jsonFile" : "target-std_srvs__rosidl_typesupport_c-Debug-4d94bf45eb9b562efdc0.json",
					"name" : "std_srvs__rosidl_typesupport_c",
					"projectIndex" : 0
				},
				{
					"directoryIndex" : 0,
					"id" : "std_srvs__rosidl_typesupport_introspection_c::@6890427a1f51a3e7e1df",
					"jsonFile" : "target-std_srvs__rosidl_typesupport_introspection_c-Debug-46223c967ae06eebe61b.json",
					"name" : "std_srvs__rosidl_typesupport_introspection_c",
					"projectIndex" : 0
				},
				{
					"directoryIndex" : 0,
					"id" : "std_srvs__rosidl_typesupport_microxrcedds_c::@6890427a1f51a3e7e1df",
					"jsonFile" : "target-std_srvs__rosidl_typesupport_microxrcedds_c-Debug-f539c641a0bd55475467.json",
					"name" : "std_srvs__rosidl_typesupport_microxrcedds_c",
					"projectIndex" : 0
				},
				{
					"directoryIndex" : 0,
					"id" : "std_srvs_uninstall::@6890427a1f51a3e7e1df",
					"jsonFile" : "target-std_srvs_uninstall-Debug-b1e35915697144d8fe3a.json",
					"name" : "std_srvs_uninstall",
					"projectIndex" : 0
				},
				{
					"directoryIndex" : 0,
					"id" : "uninstall::@6890427a1f51a3e7e1df",
					"jsonFile" : "target-uninstall-Debug-129e20fdef33f96a2357.json",
					"name" : "uninstall",
					"projectIndex" : 0
				}
			]
		}
	],
	"kind" : "codemodel",
	"paths" : 
	{
		"build" : "/home/satoimo/LEDFACE_ws/esp32_firmware_ws/firmware/mcu_ws/build/std_srvs",
		"source" : "/home/satoimo/LEDFACE_ws/esp32_firmware_ws/firmware/mcu_ws/ros2/common_interfaces/std_srvs"
	},
	"version" : 
	{
		"major" : 2,
		"minor" : 3
	}
}
